[
  {
    "caseNumber": "L01",
    "person": "Chris Watts",
    "claim": "I have no inclination of where they're at right now.",
    "currentVideoId": "3MuPWV5cTio",
    "totalResults": 0,
    "recommended": null,
    "topCandidates": [],
    "error": "HTTPError: 404 Client Error: Not Found for url: https://youglish.com/pronounce/I%20have%20no%20inclination%20of%20where%20they%27re%20at%20right%20now./english/all/emb=1&e_id=audit&e_comp=8264&e_start=1&e_h=-1&e_notif_h=1&e_cur_w=900"
  },
  {
    "caseNumber": "L02",
    "person": "Susan Smith",
    "claim": "A man carjacked me and took my boys.",
    "currentVideoId": "KPPUHvMyBUs",
    "totalResults": 0,
    "recommended": null,
    "topCandidates": [],
    "error": "HTTPError: 404 Client Error: Not Found for url: https://youglish.com/pronounce/A%20man%20carjacked%20me%20and%20took%20my%20boys./english/all/emb=1&e_id=audit&e_comp=8264&e_start=1&e_h=-1&e_notif_h=1&e_cur_w=900"
  },
  {
    "caseNumber": "L03",
    "person": "Diane Downs",
    "claim": "A bushy-haired stranger shot my children.",
    "currentVideoId": "Enghvd9o2As",
    "totalResults": 0,
    "recommended": null,
    "topCandidates": [],
    "error": "HTTPError: 404 Client Error: Not Found for url: https://youglish.com/pronounce/A%20bushy-haired%20stranger%20shot%20my%20children./english/all/emb=1&e_id=audit&e_comp=8264&e_start=1&e_h=-1&e_notif_h=1&e_cur_w=900"
  },
  {
    "caseNumber": "L04",
    "person": "Jodi Arias",
    "claim": "I wasn't there when Travis was killed.",
    "currentVideoId": "ez-4b-yQGzg",
    "totalResults": 0,
    "recommended": null,
    "topCandidates": [],
    "error": "HTTPError: 404 Client Error: Not Found for url: https://youglish.com/pronounce/I%20wasn%27t%20there%20when%20Travis%20was%20killed./english/all/emb=1&e_id=audit&e_comp=8264&e_start=1&e_h=-1&e_notif_h=1&e_cur_w=900"
  },
  {
    "caseNumber": "L05",
    "person": "Casey Anthony",
    "claim": "A nanny named Zenaida took Caylee.",
    "currentVideoId": "ixzDBcMTnV8",
    "totalResults": 0,
    "recommended": null,
    "topCandidates": [],
    "error": "HTTPError: 404 Client Error: Not Found for url: https://youglish.com/pronounce/A%20nanny%20named%20Zenaida%20took%20Caylee./english/all/emb=1&e_id=audit&e_comp=8264&e_start=1&e_h=-1&e_notif_h=1&e_cur_w=900"
  },
  {
    "caseNumber": "L06",
    "person": "Ted Bundy",
    "claim": "I am innocent.",
    "currentVideoId": "SmiiY1rQDVk",
    "totalResults": 78,
    "recommended": null,
    "topCandidates": [
      {
        "videoId": "_er8jURZbJk",
        "statementStart": 234.0,
        "statementEnd": 239.0,
        "display": "I couldn't avoid the pun of calling my piece 'I am Innocent'.",
        "zone": "2",
        "source": "YT",
        "captionId": "12929186",
        "oembed": {
          "status": 200,
          "title": "Mark Wallinger | Dulwich Picture Gallery | Van Dyck: A Masterpiece for Everyone",
          "author_name": "National Portrait Gallery",
          "author_url": "https://www.youtube.com/@nationalportraitgallery",
          "type": "video",
          "height": 113,
          "width": 200,
          "version": "1.0",
          "provider_name": "YouTube",
          "provider_url": "https://www.youtube.com/",
          "thumbnail_height": 360,
          "thumbnail_width": 480,
          "thumbnail_url": "https://i.ytimg.com/vi/_er8jURZbJk/hqdefault.jpg",
          "html": "<iframe width=\"200\" height=\"113\" src=\"https://www.youtube.com/embed/_er8jURZbJk?feature=oembed\" frameborder=\"0\" allow=\"accelerometer; autoplay; clipboard-write; encrypted-media; gyroscope; picture-in-picture; web-share\" referrerpolicy=\"strict-origin-when-cross-origin\" allowfullscreen title=\"Mark Wallinger | Dulwich Picture Gallery | Van Dyck: A Masterpiece for Everyone\"></iframe>"
        },
        "videoDurationSeconds": 312,
        "hasFullContext": true,
        "score": 24.0
      },
      {
        "videoId": "z9rvRsWKDx0",
        "statementStart": 2354.0,
        "statementEnd": 2356.0,
        "display": "that I am innocent when you are technically",
        "zone": "1",
        "source": "YT",
        "captionId": "90773994",
        "oembed": {
          "status": 200,
          "title": "Joy James: The Architects of Abolitionism",
          "author_name": "Brown University",
          "author_url": "https://www.youtube.com/@brownuniversity",
          "type": "video",
          "height": 113,
          "width": 200,
          "version": "1.0",
          "provider_name": "YouTube",
          "provider_url": "https://www.youtube.com/",
          "thumbnail_height": 360,
          "thumbnail_width": 480,
          "thumbnail_url": "https://i.ytimg.com/vi/z9rvRsWKDx0/hqdefault.jpg",
          "html": "<iframe width=\"200\" height=\"113\" src=\"https://www.youtube.com/embed/z9rvRsWKDx0?feature=oembed\" frameborder=\"0\" allow=\"accelerometer; autoplay; clipboard-write; encrypted-media; gyroscope; picture-in-picture; web-share\" referrerpolicy=\"strict-origin-when-cross-origin\" allowfullscreen title=\"Joy James: The Architects of Abolitionism\"></iframe>"
        },
        "videoDurationSeconds": 6352,
        "hasFullContext": true,
        "score": 24.0
      },
      {
        "videoId": "z9rvRsWKDx0",
        "statementStart": 2343.0,
        "statementEnd": 2346.0,
        "display": "Davis's argument has to be, I am innocent.",
        "zone": "1",
        "source": "YT",
        "captionId": "90773989",
        "oembed": {
          "status": 200,
          "title": "Joy James: The Architects of Abolitionism",
          "author_name": "Brown University",
          "author_url": "https://www.youtube.com/@brownuniversity",
          "type": "video",
          "height": 113,
          "width": 200,
          "version": "1.0",
          "provider_name": "YouTube",
          "provider_url": "https://www.youtube.com/",
          "thumbnail_height": 360,
          "thumbnail_width": 480,
          "thumbnail_url": "https://i.ytimg.com/vi/z9rvRsWKDx0/hqdefault.jpg",
          "html": "<iframe width=\"200\" height=\"113\" src=\"https://www.youtube.com/embed/z9rvRsWKDx0?feature=oembed\" frameborder=\"0\" allow=\"accelerometer; autoplay; clipboard-write; encrypted-media; gyroscope; picture-in-picture; web-share\" referrerpolicy=\"strict-origin-when-cross-origin\" allowfullscreen title=\"Joy James: The Architects of Abolitionism\"></iframe>"
        },
        "videoDurationSeconds": 6352,
        "hasFullContext": true,
        "score": 24.0
      },
      {
        "videoId": "5gnlhmaM-dM",
        "statementStart": 854.0,
        "statementEnd": 858.0,
        "display": "I am innocent of this man's blood. I AM INNOCENT OF THIS MAN'S BLOOD!",
        "zone": "2",
        "source": "YT",
        "captionId": "97737680",
        "oembed": {
          "status": 200,
          "title": "Elon Musk | Philosophy Tube",
          "author_name": "Philosophy Tube",
          "author_url": "https://www.youtube.com/@PhilosophyTube",
          "type": "video",
          "height": 113,
          "width": 200,
          "version": "1.0",
          "provider_name": "YouTube",
          "provider_url": "https://www.youtube.com/",
          "thumbnail_height": 360,
          "thumbnail_width": 480,
          "thumbnail_url": "https://i.ytimg.com/vi/5gnlhmaM-dM/hqdefault.jpg",
          "html": "<iframe width=\"200\" height=\"113\" src=\"https://www.youtube.com/embed/5gnlhmaM-dM?feature=oembed\" frameborder=\"0\" allow=\"accelerometer; autoplay; clipboard-write; encrypted-media; gyroscope; picture-in-picture; web-share\" referrerpolicy=\"strict-origin-when-cross-origin\" allowfullscreen title=\"Elon Musk | Philosophy Tube\"></iframe>"
        },
        "videoDurationSeconds": 1638,
        "hasFullContext": true,
        "score": 24.0
      },
      {
        "videoId": "D0-YwPXV-LY",
        "statementStart": 198.0,
        "statementEnd": 204.0,
        "display": "[Minnie Dean] I have nothing to say, except that I am innocent. Thank you.",
        "zone": "18",
        "source": "YT",
        "captionId": "93109031",
        "oembed": {
          "status": 200,
          "title": "The Winton baby farmer - Roadside Stories",
          "author_name": "ManatuTaonga",
          "author_url": "https://www.youtube.com/@ManatuTaonga",
          "type": "video",
          "height": 113,
          "width": 200,
          "version": "1.0",
          "provider_name": "YouTube",
          "provider_url": "https://www.youtube.com/",
          "thumbnail_height": 360,
          "thumbnail_width": 480,
          "thumbnail_url": "https://i.ytimg.com/vi/D0-YwPXV-LY/hqdefault.jpg",
          "html": "<iframe width=\"200\" height=\"113\" src=\"https://www.youtube.com/embed/D0-YwPXV-LY?feature=oembed\" frameborder=\"0\" allow=\"accelerometer; autoplay; clipboard-write; encrypted-media; gyroscope; picture-in-picture; web-share\" referrerpolicy=\"strict-origin-when-cross-origin\" allowfullscreen title=\"The Winton baby farmer - Roadside Stories\"></iframe>"
        },
        "videoDurationSeconds": 219,
        "hasFullContext": true,
        "score": 24.0
      }
    ],
    "error": null
  },
  {
    "caseNumber": "L07",
    "person": "John Wayne Gacy",
    "claim": "I don't believe I killed anybody.",
    "currentVideoId": "yQ4AT4q2DKs",
    "totalResults": 0,
    "recommended": null,
    "topCandidates": [],
    "error": "HTTPError: 404 Client Error: Not Found for url: https://youglish.com/pronounce/I%20don%27t%20believe%20I%20killed%20anybody./english/all/emb=1&e_id=audit&e_comp=8264&e_start=1&e_h=-1&e_notif_h=1&e_cur_w=900"
  },
  {
    "caseNumber": "L08",
    "person": "Stephen McDaniel",
    "claim": "I don't know what happened to Lauren.",
    "currentVideoId": "YzbIhWu0gpQ",
    "totalResults": 0,
    "recommended": null,
    "topCandidates": [],
    "error": "HTTPError: 404 Client Error: Not Found for url: https://youglish.com/pronounce/I%20don%27t%20know%20what%20happened%20to%20Lauren./english/all/emb=1&e_id=audit&e_comp=8264&e_start=1&e_h=-1&e_notif_h=1&e_cur_w=900"
  },
  {
    "caseNumber": "L09",
    "person": "Jennifer Pan",
    "claim": "Intruders tied me up and attacked my parents.",
    "currentVideoId": "amHb2UoVZ_g",
    "totalResults": 0,
    "recommended": null,
    "topCandidates": [],
    "error": "HTTPError: 404 Client Error: Not Found for url: https://youglish.com/pronounce/Intruders%20tied%20me%20up%20and%20attacked%20my%20parents./english/all/emb=1&e_id=audit&e_comp=8264&e_start=1&e_h=-1&e_notif_h=1&e_cur_w=900"
  },
  {
    "caseNumber": "L10",
    "person": "Sarah Boone",
    "claim": "It was not intentional. We were playing hide-and-seek.",
    "currentVideoId": "9dhV651zp1o",
    "totalResults": 0,
    "recommended": null,
    "topCandidates": [],
    "error": "HTTPError: 404 Client Error: Not Found for url: https://youglish.com/pronounce/It%20was%20not%20intentional.%20We%20were%20playing%20hide-and-seek./english/all/emb=1&e_id=audit&e_comp=8264&e_start=1&e_h=-1&e_notif_h=1&e_cur_w=900"
  },
  {
    "caseNumber": "L11",
    "person": "Trevor Milton",
    "claim": "The Nikola One is fully functioning.",
    "currentVideoId": "DbXqiSYDhrA",
    "totalResults": 0,
    "recommended": null,
    "topCandidates": [],
    "error": "HTTPError: 404 Client Error: Not Found for url: https://youglish.com/pronounce/The%20Nikola%20One%20is%20fully%20functioning./english/all/emb=1&e_id=audit&e_comp=8264&e_start=1&e_h=-1&e_notif_h=1&e_cur_w=900"
  },
  {
    "caseNumber": "L12",
    "person": "Bernie Madoff",
    "claim": "In today's regulatory environment, it's virtually impossible to violate the rules undetected.",
    "currentVideoId": "auTG_X2jG3E",
    "totalResults": 0,
    "recommended": null,
    "topCandidates": [],
    "error": "params.jsonData not found"
  },
  {
    "caseNumber": "L13",
    "person": "Lance Armstrong",
    "claim": "I have never doped.",
    "currentVideoId": "25ja7IAxQjY",
    "totalResults": 0,
    "recommended": null,
    "topCandidates": [],
    "error": "HTTPError: 404 Client Error: Not Found for url: https://youglish.com/pronounce/I%20have%20never%20doped./english/all/emb=1&e_id=audit&e_comp=8264&e_start=1&e_h=-1&e_notif_h=1&e_cur_w=900"
  },
  {
    "caseNumber": "L14",
    "person": "Stephanie Lazarus",
    "claim": "I barely knew Sherri Rasmussen.",
    "currentVideoId": "lC3va1aob3g",
    "totalResults": 0,
    "recommended": null,
    "topCandidates": [],
    "error": "HTTPError: 404 Client Error: Not Found for url: https://youglish.com/pronounce/I%20barely%20knew%20Sherri%20Rasmussen./english/all/emb=1&e_id=audit&e_comp=8264&e_start=1&e_h=-1&e_notif_h=1&e_cur_w=900"
  },
  {
    "caseNumber": "L15",
    "person": "Pete Rose",
    "claim": "I never bet on baseball.",
    "currentVideoId": "h4fmEbgKeh0",
    "totalResults": 0,
    "recommended": null,
    "topCandidates": [],
    "error": "params.jsonData not found"
  },
  {
    "caseNumber": "L16",
    "person": "Bill Clinton",
    "claim": "I did not have sexual relations with that woman, Miss Lewinsky.",
    "currentVideoId": "TM8EXwemnYA",
    "totalResults": 0,
    "recommended": null,
    "topCandidates": [],
    "error": "params.jsonData not found"
  },
  {
    "caseNumber": "L17",
    "person": "Kenneth Lay",
    "claim": "The company is fundamentally strong.",
    "currentVideoId": "S3EVIeZNHJU",
    "totalResults": 0,
    "recommended": null,
    "topCandidates": [],
    "error": "params.jsonData not found"
  },
  {
    "caseNumber": "L18",
    "person": "Richard Nixon",
    "claim": "I am not a crook.",
    "currentVideoId": "sh163n1lJ4M",
    "totalResults": 0,
    "recommended": null,
    "topCandidates": [],
    "error": "params.jsonData not found"
  },
  {
    "caseNumber": "L19",
    "person": "Chandler Halderson",
    "claim": "My parents went to their cabin for the weekend.",
    "currentVideoId": "MVVmLa1vKio",
    "totalResults": 0,
    "recommended": null,
    "topCandidates": [],
    "error": "params.jsonData not found"
  },
  {
    "caseNumber": "L20",
    "person": "Richard Heene",
    "claim": "It was not a hoax.",
    "currentVideoId": "_5AlMWoIRB4",
    "totalResults": 0,
    "recommended": null,
    "topCandidates": [],
    "error": "params.jsonData not found"
  },
  {
    "caseNumber": "L21",
    "person": "Hillary Clinton",
    "claim": "We landed under sniper fire.",
    "currentVideoId": "K0neF55UC-4",
    "totalResults": 0,
    "recommended": null,
    "topCandidates": [],
    "error": "params.jsonData not found"
  },
  {
    "caseNumber": "L22",
    "person": "Sean Spicer",
    "claim": "This was the largest audience ever to witness an inauguration, period.",
    "currentVideoId": "X2VKQfX5tSE",
    "totalResults": 0,
    "recommended": null,
    "topCandidates": [],
    "error": "params.jsonData not found"
  },
  {
    "caseNumber": "L23",
    "person": "Tobacco executives",
    "claim": "I believe nicotine is not addictive.",
    "currentVideoId": "jOxVk_DhWes",
    "totalResults": 0,
    "recommended": null,
    "topCandidates": [],
    "error": "params.jsonData not found"
  },
  {
    "caseNumber": "L24",
    "person": "Alex Jones",
    "claim": "Sandy Hook was fake, with actors.",
    "currentVideoId": "EdwfKrdUW1s",
    "totalResults": 0,
    "recommended": null,
    "topCandidates": [],
    "error": "params.jsonData not found"
  },
  {
    "caseNumber": "L25",
    "person": "Sherri Papini",
    "claim": "Two women kidnapped and held me captive.",
    "currentVideoId": "GjjkyscsZR8",
    "totalResults": 0,
    "recommended": null,
    "topCandidates": [],
    "error": "params.jsonData not found"
  },
  {
    "caseNumber": "T01",
    "person": "Dennis Rader",
    "claim": "I killed ten people.",
    "currentVideoId": "_yrRC1j7qeo",
    "totalResults": 0,
    "recommended": null,
    "topCandidates": [],
    "error": "params.jsonData not found"
  },
  {
    "caseNumber": "T02",
    "person": "Jeffrey Dahmer",
    "claim": "I killed seventeen people.",
    "currentVideoId": "RUEnhXunarw",
    "totalResults": 0,
    "recommended": null,
    "topCandidates": [],
    "error": "params.jsonData not found"
  },
  {
    "caseNumber": "T03",
    "person": "Edmund Kemper",
    "claim": "I killed my mother.",
    "currentVideoId": "MKK3XDI7wTE",
    "totalResults": 0,
    "recommended": null,
    "topCandidates": [],
    "error": "params.jsonData not found"
  },
  {
    "caseNumber": "T04",
    "person": "Aileen Wuornos",
    "claim": "I killed seven men.",
    "currentVideoId": "ToXjwzwaq3Y",
    "totalResults": 0,
    "recommended": null,
    "topCandidates": [],
    "error": "params.jsonData not found"
  },
  {
    "caseNumber": "T05",
    "person": "Russell Williams",
    "claim": "I killed Jessica Lloyd.",
    "currentVideoId": "hzh3adTWZOg",
    "totalResults": 0,
    "recommended": null,
    "topCandidates": [],
    "error": "params.jsonData not found"
  },
  {
    "caseNumber": "T06",
    "person": "Chris Watts",
    "claim": "I killed Shanann.",
    "currentVideoId": "eWsXwpgCG8Q",
    "totalResults": 0,
    "recommended": null,
    "topCandidates": [],
    "error": "params.jsonData not found"
  },
  {
    "caseNumber": "T07",
    "person": "Jodi Arias",
    "claim": "Yes, I killed Travis.",
    "currentVideoId": "Qvde4s--GrM",
    "totalResults": 0,
    "recommended": null,
    "topCandidates": [],
    "error": "params.jsonData not found"
  },
  {
    "caseNumber": "T08",
    "person": "Alex Murdaugh",
    "claim": "I lied about being at the kennels.",
    "currentVideoId": "rEXrNoyv4Q8",
    "totalResults": 0,
    "recommended": null,
    "topCandidates": [],
    "error": "params.jsonData not found"
  },
  {
    "caseNumber": "T09",
    "person": "Richard Jewell",
    "claim": "I did not plant the Olympic Park bomb.",
    "currentVideoId": "DPMOiJIayPc",
    "totalResults": 0,
    "recommended": null,
    "topCandidates": [],
    "error": "params.jsonData not found"
  },
  {
    "caseNumber": "T10",
    "person": "Lindy Chamberlain",
    "claim": "A dingo took my baby.",
    "currentVideoId": "WRyeAkP17aM",
    "totalResults": 0,
    "recommended": null,
    "topCandidates": [],
    "error": "params.jsonData not found"
  },
  {
    "caseNumber": "T11",
    "person": "Kirk Bloodsworth",
    "claim": "DNA proved I did not commit the murder.",
    "currentVideoId": "q47wkZXczwY",
    "totalResults": 0,
    "recommended": null,
    "topCandidates": [],
    "error": "params.jsonData not found"
  },
  {
    "caseNumber": "T12",
    "person": "Anthony Ray Hinton",
    "claim": "I spent thirty years on death row for a crime I did not commit.",
    "currentVideoId": "po2ui6EYW8Y",
    "totalResults": 0,
    "recommended": null,
    "topCandidates": [],
    "error": "params.jsonData not found"
  },
  {
    "caseNumber": "T13",
    "person": "Elizabeth Smart",
    "claim": "I was held captive for nine months.",
    "currentVideoId": "2w-ZdPkNvFY",
    "totalResults": 0,
    "recommended": null,
    "topCandidates": [],
    "error": "params.jsonData not found"
  },
  {
    "caseNumber": "T14",
    "person": "Jaycee Dugard",
    "claim": "I was held captive for eighteen years.",
    "currentVideoId": "yXRPgKLnWnU",
    "totalResults": 0,
    "recommended": null,
    "topCandidates": [],
    "error": "params.jsonData not found"
  },
  {
    "caseNumber": "T15",
    "person": "Mary Vincent",
    "claim": "He cut off both my arms, and I survived.",
    "currentVideoId": "W259o2tO2pc",
    "totalResults": 0,
    "recommended": null,
    "topCandidates": [],
    "error": "params.jsonData not found"
  },
  {
    "caseNumber": "T16",
    "person": "Aron Ralston",
    "claim": "I cut off my own arm to survive.",
    "currentVideoId": "idLfpNH5KTc",
    "totalResults": 0,
    "recommended": null,
    "topCandidates": [],
    "error": "params.jsonData not found"
  },
  {
    "caseNumber": "T17",
    "person": "Harrison Okene",
    "claim": "I survived nearly three days in an air pocket inside a sunken ship.",
    "currentVideoId": "qevehxLe2s4",
    "totalResults": 0,
    "recommended": null,
    "topCandidates": [],
    "error": "params.jsonData not found"
  },
  {
    "caseNumber": "T18",
    "person": "Ricky Megee",
    "claim": "I survived 71 days alone in the Australian outback.",
    "currentVideoId": "Ka0MVmd5Tes",
    "totalResults": 0,
    "recommended": null,
    "topCandidates": [],
    "error": "params.jsonData not found"
  },
  {
    "caseNumber": "T19",
    "person": "Robert Downey Jr.",
    "claim": "My addiction led to prison.",
    "currentVideoId": "mFol0tP0pGg",
    "totalResults": 0,
    "recommended": null,
    "topCandidates": [],
    "error": "params.jsonData not found"
  },
  {
    "caseNumber": "T20",
    "person": "Mike Tyson",
    "claim": "I bit Evander Holyfield's ear.",
    "currentVideoId": "qC4AG8x2768",
    "totalResults": 0,
    "recommended": null,
    "topCandidates": [],
    "error": "params.jsonData not found"
  },
  {
    "caseNumber": "T21",
    "person": "Michael Packard",
    "claim": "A humpback whale had me inside its mouth and spit me back out.",
    "currentVideoId": "K7iAlZzVenU",
    "totalResults": 0,
    "recommended": null,
    "topCandidates": [],
    "error": "params.jsonData not found"
  },
  {
    "caseNumber": "T22",
    "person": "Sammy Gravano",
    "claim": "I was involved in nineteen murders.",
    "currentVideoId": "diqdKgEzOkE",
    "totalResults": 0,
    "recommended": null,
    "topCandidates": [],
    "error": "params.jsonData not found"
  },
  {
    "caseNumber": "T23",
    "person": "Paul Templer",
    "claim": "I was trapped inside a hippo's mouth and survived repeated attacks.",
    "currentVideoId": "sjVgpvlzrXM",
    "totalResults": 0,
    "recommended": null,
    "topCandidates": [],
    "error": "params.jsonData not found"
  },
  {
    "caseNumber": "T24",
    "person": "Michael Morton",
    "claim": "I spent nearly 25 years in prison for my wife's murder, but DNA proved I was innocent.",
    "currentVideoId": "kv3j7yd7kTk",
    "totalResults": 0,
    "recommended": null,
    "topCandidates": [],
    "error": "params.jsonData not found"
  },
  {
    "caseNumber": "T25",
    "person": "Lance Armstrong",
    "claim": "I used banned substances during my Tour victories.",
    "currentVideoId": "FRXzbNReCR0",
    "totalResults": 0,
    "recommended": null,
    "topCandidates": [],
    "error": "params.jsonData not found"
  }
]
